log2compdb/__init__.py
log2compdb/__main__.py
log2compdb-0.2.5.dist-info/LICENSE
log2compdb-0.2.5.dist-info/METADATA
log2compdb-0.2.5.dist-info/WHEEL
log2compdb-0.2.5.dist-info/entry_points.txt
log2compdb-0.2.5.dist-info/top_level.txt
log2compdb-0.2.5.dist-info/RECORD
