Metadata-Version: 2.1
Name: log2compdb
Version: 0.2.5
Summary: Generate compile_commands.json from a build log with compiler invocations
Home-page: https://github.com/Qyriad/log2compdb
Author: Qyriad
Author-email: qyriad@qyriad.me
License: MIT
Keywords: build-tool,build-system,compilation-database
Platform: any
License-File: LICENSE
Provides-Extra: dev
Requires-Dist: pytest >=7.0 ; extra == 'dev'
